poser/__init__.py
poser/_loader.py
poser/_version.py
poser/_widget.py
poser/napari.yaml
poser/utils.py
poser/_tests/__init__.py
poser/_tests/decoder_config.yml
poser/_tests/test_DLC_file.h5
poser/_tests/test_classification_file.h5
poser/_tests/test_video.avi
poser/_tests/test_widget.py
poser/_tests/lightning_logs/version_106/epoch=14-step=479.ckpt
poser/_tests/lightning_logs/version_106/events.out.tfevents.1659367239.kennedy13.143666.0
poser/_tests/lightning_logs/version_106/hparams.yaml
poser/models/__init__.py
poser/models/c3d.py
poser/models/gconv.py
poser/models/gconv_origin.py
poser/models/graph.py
poser/models/st_gcn_aaai18_pylightning.py
poser/models/st_gcn_aaai18_pylightning_3block.py
PoseR_napari-0.0.1b4.dist-info/LICENSE
PoseR_napari-0.0.1b4.dist-info/METADATA
PoseR_napari-0.0.1b4.dist-info/WHEEL
PoseR_napari-0.0.1b4.dist-info/entry_points.txt
PoseR_napari-0.0.1b4.dist-info/top_level.txt
PoseR_napari-0.0.1b4.dist-info/RECORD
