Metadata-Version: 2.1
Name: PoseR-napari
Version: 0.0.1b4
Summary: A deep learning toolbox for decoding animal behaviour
Home-page: https://github.com/pnm4sfix/PoseR
Author: Pierce Mullen
Author-email: pnm1@st-andrews.ac.uk
License: BSD-3-Clause
Project-URL: Bug Tracker, https://github.com/pnm4sfix/PoseR/issues
Project-URL: Documentation, https://github.com/pnm4sfix/PoseR#README.md
Project-URL: Source Code, https://github.com/pnm4sfix/PoseR
Project-URL: User Support, https://github.com/pnm4sfix/PoseR/issues
Classifier: Development Status :: 2 - Pre-Alpha
Classifier: Framework :: napari
Classifier: Intended Audience :: Developers
Classifier: License :: OSI Approved :: BSD License
Classifier: Operating System :: OS Independent
Classifier: Programming Language :: Python
Classifier: Programming Language :: Python :: 3
Classifier: Programming Language :: Python :: 3 :: Only
Classifier: Programming Language :: Python :: 3.10
Classifier: Topic :: Scientific/Engineering :: Image Processing
Requires-Python: >=3.10
License-File: LICENSE
Requires-Dist: napari[all]==0.4.14
Requires-Dist: npe2==0.6.2
Requires-Dist: pydantic==1.10.4
Requires-Dist: numpy==1.23.5
Requires-Dist: magicgui
Requires-Dist: qtpy
Requires-Dist: napari-video
Requires-Dist: napari-plot==0.1.5
Requires-Dist: tables
Requires-Dist: imageio-ffmpeg==0.4.8
Requires-Dist: pytorch-lightning
Requires-Dist: test-tube
Requires-Dist: scikit-learn
Requires-Dist: matplotlib
Requires-Dist: numba
Requires-Dist: networkx
Requires-Dist: seaborn
Requires-Dist: ultralytics
Requires-Dist: torcheval==0.0.7
Provides-Extra: testing
Requires-Dist: tox; extra == "testing"
Requires-Dist: pytest; extra == "testing"
Requires-Dist: pytest-cov; extra == "testing"
Requires-Dist: pytest-qt; extra == "testing"
Requires-Dist: napari; extra == "testing"
Requires-Dist: pyqt5; extra == "testing"
